README.rst
setup.py
switchcase/__init__.py
switchcase/switchcase.py
switchcase.egg-info/PKG-INFO
switchcase.egg-info/SOURCES.txt
switchcase.egg-info/dependency_links.txt
switchcase.egg-info/top_level.txt
switchcase/tests/__init__.py
switchcase/tests/test_switch.py