Metadata-Version: 1.1
Name: switchcase
Version: 1.0
Summary: Switch-Case in pure Python
Home-page: https://github.com/ssanderson/switchcase
Author: Scott Sanderson
Author-email: scott.b.sanderson90@gmail.com
License: MIT
Platform: UNKNOWN
Classifier: License :: OSI Approved :: MIT License
Classifier: Development Status :: 4 - Beta
Classifier: Natural Language :: English
Classifier: Programming Language :: Python :: 2
Classifier: Programming Language :: Python :: 3
